bir_mcp/__init__.py
bir_mcp/config.py
bir_mcp/core.py
bir_mcp/hashicorp.py
bir_mcp/main.py
bir_mcp/utils.py
bir_mcp/atlassian/__init__.py
bir_mcp/atlassian/utils.py
bir_mcp/charts/__init__.py
bir_mcp/dataiku/__init__.py
bir_mcp/git_lab/__init__.py
bir_mcp/git_lab/annotations.py
bir_mcp/git_lab/prompts.py
bir_mcp/git_lab/sonarqube.py
bir_mcp/git_lab/tools.py
bir_mcp/git_lab/utils.py
bir_mcp/grafana/__init__.py
bir_mcp/grafana/prompts.py
bir_mcp/grafana/resources.py
bir_mcp/grafana/utils.py
bir_mcp/local/__init__.py
bir_mcp/local/filesystem.py
bir_mcp/local/git_local.py
bir_mcp/sql/__init__.py
bir_mcp-0.3.14.dist-info/METADATA
bir_mcp-0.3.14.dist-info/WHEEL
bir_mcp-0.3.14.dist-info/entry_points.txt
bir_mcp-0.3.14.dist-info/top_level.txt
bir_mcp-0.3.14.dist-info/RECORD
