Metadata-Version: 2.4
Name: bir_mcp
Version: 0.3.14
Summary: MCP server for BirBank
Requires-Python: <3.14,>=3.12
Requires-Dist: altair>=5.5.0
Requires-Dist: atlassian-python-api>=4.0.4
Requires-Dist: bidict>=0.23.1
Requires-Dist: cachetools>=5.5.2
Requires-Dist: detect-secrets>=1.5.0
Requires-Dist: fastapi>=0.116.1
Requires-Dist: fastmcp>=2.10.2
Requires-Dist: gitpython>=3.1.44
Requires-Dist: langchain>=0.3.26
Requires-Dist: langchain-community>=0.3.27
Requires-Dist: markdownify>=1.2.0
Requires-Dist: oracledb>=3.2.0
Requires-Dist: pandas>=2.3.1
Requires-Dist: py-consul>=1.6.0
Requires-Dist: python-gitlab[graphql]>=6.1.0
Requires-Dist: tiktoken>=0.11.0
Requires-Dist: typer>=0.16.0
Requires-Dist: vl-convert-python>=1.8.0
